{
  "required": true,
  "minVersion": "0.8",
  "package": "ru.galster.crashfabric.mixin",
  "compatibilityLevel": "JAVA_17",
  "mixins": [
    "DontCrashOnPlayerRemove$DistanceManagerMixin",
    "DoublePlayerChunkMap$ChunkMapMixin",
    "DoublePlayerChunkMap$EntityMixin",
    "DoublePlayerChunkMap$ServerLevelMixin",
    "FixCocoaDecoratorGeneration$CocoaDecoratorMixin",
    "LargeMoveVectors$ServerGamePacketListenerImplMixin",
    "PreventEntityCrash$LevelChunkMixin",
    "PreventEntityCrash$LevelMixin",
    "fakes.ServerGamePacketListenerImplAccessor"
  ],
  "client": [
  ],
  "injectors": {
    "defaultRequire": 1
  }
}
